{
	"files": [

	],
	"folders": {
		"Characters": {
			"files": [
				"character-1660859944.json",
				"character-1660859986.json",
				"character-1681588545.json"
			],
			"folders": {

			},
			"metadata": {
				"color": null,
				"folded": false
			}
		},
		"Definitions": {
			"files": [

			],
			"folders": {

			},
			"metadata": {
				"color": null,
				"folded": false
			}
		},
		"Themes": {
			"files": [
				"default-theme.cfg"
			],
			"folders": {

			},
			"metadata": {
				"color": null,
				"folded": false
			}
		},
		"Timelines": {
			"files": [
				"timeline-1660859960.json",
				"timeline-1660862297.json",
				"timeline-1661043200.json",
				"timeline-1681588556.json"
			],
			"folders": {

			},
			"metadata": {
				"color": null,
				"folded": false
			}
		}
	}
}
